[
    {
        "title": "Helmet",
        "ques": "What is the purpose of the **Helmet** middleware in Express?",
        "answer": {
            "type": "text",
            "content": "It secures Express apps by setting various **HTTP Headers**.\n\nIt hides the `X-Powered-By` header (which reveals you use Express), sets XSS protection, and configures HSTS (Strict Transport Security)."
        },
        "explanation": "The easiest security win for Express."
    },
    {
        "title": "Rate Limiting",
        "ques": "Why should you implement **Rate Limiting**?",
        "answer": {
            "type": "text",
            "content": "To prevent **Brute Force** attacks and **DDoS**.\n\nIt limits the number of requests a single IP address can make in a given timeframe (e.g., 5 login attempts per minute)."
        },
        "explanation": "Use `express-rate-limit`."
    },
    {
        "title": "Input Validation",
        "ques": "Why is trusting `req.body` directly a security risk?",
        "answer": {
            "type": "text",
            "content": "**Injection Attacks (SQL/NoSQL) and Pollution.**\n\nAlways validate and sanitize input using a library like **Joi** or **express-validator** before using it in logic or database queries."
        },
        "explanation": "Never trust the client."
    },
    {
        "title": "CORS",
        "ques": "What does `cors()` middleware do?",
        "answer": {
            "type": "text",
            "content": "It acts as a gatekeeper for **Cross-Origin Resource Sharing**.\n\nIt determines which domains are allowed to access your API. By default, browsers block cross-domain requests. CORS headers tell the browser \"It's okay, let `my-frontend.com` read this data\"."
        },
        "explanation": "Configure it explicitly for your domain."
    }
]